growatt/__init__.py
growatt_api-0.1.4.dist-info/METADATA
growatt_api-0.1.4.dist-info/WHEEL
growatt_api-0.1.4.dist-info/top_level.txt
growatt_api-0.1.4.dist-info/RECORD
