Metadata-Version: 2.1
Name: growatt-api
Version: 0.1.4
Summary: A Python wrapper for Growatt API
Home-page: https://github.com/brandonbondig/growatt
Author: Brandon Bondig
Author-email: brandon@bondig.dk
Classifier: Programming Language :: Python :: 3
Classifier: License :: OSI Approved :: MIT License
Classifier: Operating System :: OS Independent
Requires-Python: >=3.6
Requires-Dist: requests
